yamlcredits/main.py
yamlcredits-1.0.0.data/scripts/yamlcredits
yamlcredits-1.0.0.dist-info/LICENSE
yamlcredits-1.0.0.dist-info/METADATA
yamlcredits-1.0.0.dist-info/WHEEL
yamlcredits-1.0.0.dist-info/top_level.txt
yamlcredits-1.0.0.dist-info/RECORD
